[{"filename":"en","language":"eng3.txt","keywords":[{"keyword":"investment","value":7.6246189861593985},{"keyword":"leverage","value":6.238324625039508},{"keyword":"money","value":5.545177444479562},{"keyword":"property","value":4.1588830833596715},{"keyword":"leveraged","value":3.4657359027997265},{"keyword":"loan","value":3.4657359027997265},{"keyword":"borrow","value":2.772588722239781},{"keyword":"lose","value":2.772588722239781},{"keyword":"value","value":2.772588722239781},{"keyword":"owe","value":2.772588722239781},{"keyword":"profit","value":2.772588722239781},{"keyword":"financial","value":2.772588722239781},{"keyword":"market","value":2.0794415416798357},{"keyword":"risky","value":2.0794415416798357},{"keyword":"buy","value":2.0794415416798357},{"keyword":"tear","value":2.0794415416798357},{"keyword":"worth","value":2.0794415416798357},{"keyword":"institution","value":2.0794415416798357},{"keyword":"ratio","value":2.0794415416798357},{"keyword":"meltdown","value":2.0794415416798357},{"keyword":"economy","value":1.3862943611198906},{"keyword":"lead","value":1.3862943611198906},{"keyword":"technique","value":1.3862943611198906},{"keyword":"normal","value":1.3862943611198906},{"keyword":"bad","value":1.3862943611198906},{"keyword":"bubble","value":1.3862943611198906},{"keyword":"need","value":1.3862943611198906},{"keyword":"downturn","value":1.3862943611198906},{"keyword":"factor","value":1.3862943611198906},{"keyword":"repeat","value":1.3862943611198906}]},{"filename":"en","language":"eng2.txt","keywords":[{"keyword":"light","value":16.635532333438686},{"keyword":"speed","value":11.78350206951907},{"keyword":"travel","value":10.39720770839918},{"keyword":"theory","value":8.317766166719343},{"keyword":"gravity","value":7.6246189861593985},{"keyword":"relativity","value":7.6246189861593985},{"keyword":"black","value":6.238324625039508},{"keyword":"clock","value":6.238324625039508},{"keyword":"longer","value":5.545177444479562},{"keyword":"weird","value":5.545177444479562},{"keyword":"really","value":4.852030263919617},{"keyword":"sec","value":4.852030263919617},{"keyword":"slowly","value":4.852030263919617},{"keyword":"earth","value":4.852030263919617},{"keyword":"live","value":4.852030263919617},{"keyword":"photon","value":4.852030263919617},{"keyword":"star","value":4.1588830833596715},{"keyword":"past","value":4.1588830833596715},{"keyword":"space","value":4.027549014324932},{"keyword":"sun","value":3.4657359027997265},{"keyword":"field","value":3.4657359027997265},{"keyword":"einstein","value":3.4657359027997265},{"keyword":"ruler","value":3.4657359027997265},{"keyword":"spaceship","value":3.4657359027997265},{"keyword":"gravitational","value":3.4657359027997265},{"keyword":"spacecraft","value":3.4657359027997265},{"keyword":"universe","value":3.4657359027997265},{"keyword":"length","value":3.4657359027997265},{"keyword":"hole","value":3.164502796969589},{"keyword":"dense","value":2.772588722239781}]},{"filename":"en","language":"eng1.txt","keywords":[{"keyword":"canyon","value":9.704060527839234},{"keyword":"arm","value":5.545177444479562},{"keyword":"hand","value":4.1588830833596715},{"keyword":"right","value":3.4657359027997265},{"keyword":"boulder","value":3.4657359027997265},{"keyword":"desert","value":3.4657359027997265},{"keyword":"try","value":3.4657359027997265},{"keyword":"knife","value":3.4657359027997265},{"keyword":"water","value":2.772588722239781},{"keyword":"wall","value":2.772588722239781},{"keyword":"strap","value":2.0794415416798357},{"keyword":"bleed","value":2.0794415416798357},{"keyword":"climb","value":2.0794415416798357},{"keyword":"take","value":2.0794415416798357},{"keyword":"rock","value":2.0794415416798357},{"keyword":"walk","value":2.0794415416798357},{"keyword":"minute","value":2.0794415416798357},{"keyword":"aaron","value":2.0794415416798357},{"keyword":"blue","value":2.0794415416798357},{"keyword":"three","value":2.0794415416798357},{"keyword":"weight","value":2.0794415416798357},{"keyword":"blade","value":2.0794415416798357},{"keyword":"experience","value":2.0794415416798357},{"keyword":"ralston","value":2.0794415416798357},{"keyword":"death","value":2.0794415416798357},{"keyword":"soon","value":2.0794415416798357},{"keyword":"day","value":1.7260924347106852},{"keyword":"steep","value":1.3862943611198906},{"keyword":"multitool","value":1.3862943611198906},{"keyword":"skin","value":1.3862943611198906}]}]